LICENSE
MANIFEST.in
README.rst
git-lab
requirements.txt
setup.py
git_lab/__init__.py
git_lab/config.py
git_lab/utils.py
git_lab.egg-info/PKG-INFO
git_lab.egg-info/SOURCES.txt
git_lab.egg-info/dependency_links.txt
git_lab.egg-info/requires.txt
git_lab.egg-info/top_level.txt
git_lab/apis/__init__.py
git_lab/apis/mergerequest/__init__.py
git_lab/apis/mergerequest/models.py
git_lab/apis/mergerequest/repositories.py
git_lab/apis/mergerequest/services.py
git_lab/apis/projects/__init__.py
git_lab/apis/projects/models.py
git_lab/apis/projects/repositories.py