Metadata-Version: 1.0
Name: git-lab
Version: 0.2.0
Summary: sub-command of git for access to gitlab
Home-page: https://github.com/kamekoopa/git-lab
Author: kamekoopa
Author-email: hogehugo@gmail.com
License: Apache 2.0
Platform: UNKNOWN
